<?xml version="1.0" encoding="UTF-8" ?>
<!DOCTYPE mapper PUBLIC "-//mybatis.org//DTD Mapper 3.0//EN" "http://mybatis.org/dtd/mybatis-3-mapper.dtd" >
<mapper namespace="com.gd.datachx.mapper.TImBranchStockMapper" >
  <resultMap id="BaseResultMap" type="com.gd.datachx.entity.TImBranchStock" >
    <!--
      WARNING - @mbggenerated
      This element is automatically generated by MyBatis Generator, do not modify.
    -->
    <result column="item_no" property="itemNo" jdbcType="CHAR" />
    <result column="branch_no" property="branchNo" jdbcType="CHAR" />
    <result column="stock_qty" property="stockQty" jdbcType="DECIMAL" />
    <result column="route_qty" property="routeQty" jdbcType="DECIMAL" />
    <result column="avg_cost" property="avgCost" jdbcType="DECIMAL" />
    <result column="cost_amt" property="costAmt" jdbcType="DECIMAL" />
    <result column="last_inprice" property="lastInprice" jdbcType="DECIMAL" />
    <result column="last_baseprice" property="lastBaseprice" jdbcType="DECIMAL" />
    <result column="min_qty" property="minQty" jdbcType="DECIMAL" />
    <result column="max_qty" property="maxQty" jdbcType="DECIMAL" />
    <result column="acc_qty" property="accQty" jdbcType="DECIMAL" />
    <result column="oper_date" property="operDate" jdbcType="TIMESTAMP" />
    <result column="com_flag" property="comFlag" jdbcType="CHAR" />
  </resultMap>
  <insert id="insert" parameterType="com.gd.datachx.entity.TImBranchStock" >
    <!--
      WARNING - @mbggenerated
      This element is automatically generated by MyBatis Generator, do not modify.
    -->
    insert into t_im_branch_stock (item_no, branch_no, stock_qty, 
      route_qty, avg_cost, cost_amt, 
      last_inprice, last_baseprice, min_qty, 
      max_qty, acc_qty, oper_date, 
      com_flag)
    values (#{itemNo,jdbcType=CHAR}, #{branchNo,jdbcType=CHAR}, #{stockQty,jdbcType=DECIMAL}, 
      #{routeQty,jdbcType=DECIMAL}, #{avgCost,jdbcType=DECIMAL}, #{costAmt,jdbcType=DECIMAL}, 
      #{lastInprice,jdbcType=DECIMAL}, #{lastBaseprice,jdbcType=DECIMAL}, #{minQty,jdbcType=DECIMAL}, 
      #{maxQty,jdbcType=DECIMAL}, #{accQty,jdbcType=DECIMAL}, #{operDate,jdbcType=TIMESTAMP}, 
      #{comFlag,jdbcType=CHAR})
  </insert>
  <insert id="insertSelective" parameterType="com.gd.datachx.entity.TImBranchStock" >
    <!--
      WARNING - @mbggenerated
      This element is automatically generated by MyBatis Generator, do not modify.
    -->
    insert into t_im_branch_stock
    <trim prefix="(" suffix=")" suffixOverrides="," >
      <if test="itemNo != null" >
        item_no,
      </if>
      <if test="branchNo != null" >
        branch_no,
      </if>
      <if test="stockQty != null" >
        stock_qty,
      </if>
      <if test="routeQty != null" >
        route_qty,
      </if>
      <if test="avgCost != null" >
        avg_cost,
      </if>
      <if test="costAmt != null" >
        cost_amt,
      </if>
      <if test="lastInprice != null" >
        last_inprice,
      </if>
      <if test="lastBaseprice != null" >
        last_baseprice,
      </if>
      <if test="minQty != null" >
        min_qty,
      </if>
      <if test="maxQty != null" >
        max_qty,
      </if>
      <if test="accQty != null" >
        acc_qty,
      </if>
      <if test="operDate != null" >
        oper_date,
      </if>
      <if test="comFlag != null" >
        com_flag,
      </if>
    </trim>
    <trim prefix="values (" suffix=")" suffixOverrides="," >
      <if test="itemNo != null" >
        #{itemNo,jdbcType=CHAR},
      </if>
      <if test="branchNo != null" >
        #{branchNo,jdbcType=CHAR},
      </if>
      <if test="stockQty != null" >
        #{stockQty,jdbcType=DECIMAL},
      </if>
      <if test="routeQty != null" >
        #{routeQty,jdbcType=DECIMAL},
      </if>
      <if test="avgCost != null" >
        #{avgCost,jdbcType=DECIMAL},
      </if>
      <if test="costAmt != null" >
        #{costAmt,jdbcType=DECIMAL},
      </if>
      <if test="lastInprice != null" >
        #{lastInprice,jdbcType=DECIMAL},
      </if>
      <if test="lastBaseprice != null" >
        #{lastBaseprice,jdbcType=DECIMAL},
      </if>
      <if test="minQty != null" >
        #{minQty,jdbcType=DECIMAL},
      </if>
      <if test="maxQty != null" >
        #{maxQty,jdbcType=DECIMAL},
      </if>
      <if test="accQty != null" >
        #{accQty,jdbcType=DECIMAL},
      </if>
      <if test="operDate != null" >
        #{operDate,jdbcType=TIMESTAMP},
      </if>
      <if test="comFlag != null" >
        #{comFlag,jdbcType=CHAR},
      </if>
    </trim>
  </insert>
  <select id="selectTitemStock"  resultMap="BaseResultMap">
    SELECT item_no, branch_no, stock_qty,
      avg_cost
    FROM t_im_branch_stock
  </select>
</mapper>